mmsw/__init__.py
mmsw/mmsw.py
mmsw/core/__init__.py
mmsw/core/config_base.py
mmsw-0.0.20.dist-info/METADATA
mmsw-0.0.20.dist-info/WHEEL
mmsw-0.0.20.dist-info/top_level.txt
mmsw-0.0.20.dist-info/RECORD
