Metadata-Version: 2.4
Name: mmsw
Version: 0.0.20
Summary: Matilo (C) Deep-Learning Model Serving Worker Module
Home-page: https://github.com/ryuvsken
Author: ryuvsken
Author-email: "Tony, K" <ryuvskendev@gmail.com>
License: BSD
Requires-Python: >=3.11
Requires-Dist: sqlalchemy==2.0.44
Requires-Dist: pymysql==1.1.2
Requires-Dist: requests==2.32.5
Dynamic: author
Dynamic: home-page
Dynamic: requires-python
